{"cameraMode":{"drawMode":0,"name":"Shaded","section":"Shading Mode"},"sceneLighting":true,"audioPlay":false,"sceneViewState":{"m_AlwaysRefresh":false,"showFog":true,"showSkybox":false,"showFlares":true,"showImageEffects":true,"showParticleSystems":true,"showVisualEffectGraphs":true,"m_FxEnabled":true},"in2DMode":false,"pivot":{"x":-8.238333702087403,"y":1.1105537414550782,"z":-2.763667345046997},"rotation":{"x":-0.17887374758720399,"y":0.7676976919174194,"z":-0.24361926317214967,"w":-0.5658287405967712},"size":0.4773775339126587,"orthographic":false}